LICENSE.txt
README.md
setup.cfg
setup.py
domino_mlflow_client/__init__.py
domino_mlflow_client/domino_mlflow_client.py
domino_mlflow_client/model_utils.py
domino_mlflow_client/service_account_utils.py
domino_mlflow_client/tag_constants.py
domino_mlflow_client.egg-info/PKG-INFO
domino_mlflow_client.egg-info/SOURCES.txt
domino_mlflow_client.egg-info/dependency_links.txt
domino_mlflow_client.egg-info/requires.txt
domino_mlflow_client.egg-info/top_level.txt