Metadata-Version: 2.1
Name: domino-mlflow-client
Version: 0.6.7
Summary: Domino client wrapper for ml flow
Home-page: https://github.com/cerebrotech/domino-mlflow-utils
Author: Sameer Wadkar , Uday Kumar Samala, Pattabi Srinivasan
Author-email: sammer.wadkar@dominodatalab.com
License: MIT
Download-URL: https://github.com/cerebrotech/domino-mlflow-utils/archive/pypi-0_1_5.tar.gz
Keywords: domino,mlflow,client
Platform: UNKNOWN
Classifier: Development Status :: 3 - Alpha
Classifier: Intended Audience :: Developers
Classifier: License :: OSI Approved :: MIT License
Classifier: Programming Language :: Python :: 3.7
Classifier: Programming Language :: Python :: 3.8
License-File: LICENSE.txt
